relog/__init__.py
relog/core.py
relog/formatting.py
relog/handler.py
relog/logger.py
relog/version.py
relogged-0.1.0.dist-info/LICENSE
relogged-0.1.0.dist-info/METADATA
relogged-0.1.0.dist-info/WHEEL
relogged-0.1.0.dist-info/top_level.txt
relogged-0.1.0.dist-info/RECORD
