Metadata-Version: 2.1
Name: relogged
Version: 0.1.0
Summary: Standardized logging in Python, revisited.
Home-page: https://gitlab.com/kyberdin/relogged
Author: Stephen Stauts
Author-email: kyberdin.git@gmail.com
License: MIT
Keywords: utilities logging
Platform: UNKNOWN
Classifier: Development Status :: 3 - Alpha
Classifier: License :: OSI Approved :: MIT License
Classifier: Operating System :: POSIX :: Linux
Classifier: Programming Language :: Python :: 3.6
Classifier: Programming Language :: Python :: 3.7
Classifier: Programming Language :: Python :: 3.8
Requires-Python: >=3.6
